[{"img_name": "sroll_17_avril_01_04.tif", "sp_name": "sroll_17_avril_01_04_digitized.dat", "sp_range": [3249, 3301], "calsp_name": "sroll_17_avril_01_04_calibrated.dat", "calsplines_name": "sroll_17_avril_01_04_digitized_cal_lines.dat"}, {"img_name": "sroll_17_avril_01_03.tif", "sp_name": "sroll_17_avril_01_03_digitized.dat", "sp_range": [3301, 3354], "calsp_name": "sroll_17_avril_01_03_calibrated.dat", "calsplines_name": "sroll_17_avril_01_03_digitized_cal_lines.dat"}, {"img_name": "sroll_17_avril_01_05.tif", "sp_name": "sroll_17_avril_01_05_digitized.dat", "sp_range": [3354, 3407], "calsp_name": "sroll_17_avril_01_05_calibrated.dat", "calsplines_name": "sroll_17_avril_01_05_digitized_cal_lines.dat"}, {"img_name": "sroll_17_avril_01_01.tif", "sp_name": "sroll_17_avril_01_01_digitized.dat", "sp_range": [3407, 3459], "calsp_name": "sroll_17_avril_01_01_calibrated.dat", "calsplines_name": "sroll_17_avril_01_01_digitized_cal_lines.dat"}, {"img_name": "sroll_17_avril_01_06.tif", "sp_name": "sroll_17_avril_01_06_digitized.dat", "sp_range": [3459, 3512], "calsp_name": "sroll_17_avril_01_06_calibrated.dat", "calsplines_name": "sroll_17_avril_01_06_digitized_cal_lines.dat"}, {"img_name": "sroll_17_avril_01_02.tif", "sp_name": "sroll_17_avril_01_02_digitized.dat", "sp_range": [3512, 3565], "calsp_name": "sroll_17_avril_01_02_calibrated.dat", "calsplines_name": "sroll_17_avril_01_02_digitized_cal_lines.dat"}, {"img_name": null, "sp_name": null, "sp_range": [], "calsp_name": null, "calsplines_name": null}, {"img_name": null, "sp_name": null, "sp_range": [], "calsp_name": null, "calsplines_name": null}, {"img_name": null, "sp_name": null, "sp_range": [], "calsp_name": null, "calsplines_name": null}, {"img_name": null, "sp_name": null, "sp_range": [], "calsp_name": null, "calsplines_name": null}, {"img_name": null, "sp_name": null, "sp_range": [], "calsp_name": null, "calsplines_name": null}, {"img_name": null, "sp_name": null, "sp_range": [], "calsp_name": null, "calsplines_name": null}]